color_bottles/__init__.py
color_bottles/core.py
color_bottles/frontend/__init__.py
color_bottles/frontend/console_front.py
color_bottles/frontend/pygame_front.py
color_bottles/play_game.py
color_bottles_puzzle-0.0.4.dist-info/LICENSE
color_bottles_puzzle-0.0.4.dist-info/WHEEL
color_bottles_puzzle-0.0.4.dist-info/entry_points.txt
color_bottles_puzzle-0.0.4.dist-info/METADATA
color_bottles_puzzle-0.0.4.dist-info/RECORD
