Metadata-Version: 2.1
Name: color-bottles-puzzle
Version: 0.0.4
Summary: Water color sort puzzle game
Home-page: https://github.com/oyvsyo/color-bottles-puzzle
License: MIT
Keywords: game,puzzle
Author: Stepan Dvoiak
Author-email: dvoiak.stepan@gmail.com
Requires-Python: >=3.7,<4.0
Classifier: License :: OSI Approved :: MIT License
Classifier: Programming Language :: Python :: 3
Classifier: Programming Language :: Python :: 3.7
Classifier: Programming Language :: Python :: 3.8
Classifier: Programming Language :: Python :: 3.9
Classifier: Programming Language :: Python :: 3.10
Classifier: Programming Language :: Python :: 3.11
Provides-Extra: pygame
Requires-Dist: colorama (>=0.4.6,<0.5.0)
Requires-Dist: pygame (>=2,<3) ; extra == "pygame"
Project-URL: Repository, https://github.com/oyvsyo/color-bottles-puzzle
